sparky_utils/__init__.py
sparky_utils/advice.py
sparky_utils/decorators.py
sparky_utils/exceptions.py
sparky_utils/list_modules.py
sparky_utils/response.py
sparky_utils/logger/__init__.py
sparky_utils-1.1.8.dist-info/LICENSE
sparky_utils-1.1.8.dist-info/METADATA
sparky_utils-1.1.8.dist-info/WHEEL
sparky_utils-1.1.8.dist-info/top_level.txt
sparky_utils-1.1.8.dist-info/RECORD
