Metadata-Version: 2.2
Name: sparky_utils
Version: 1.1.8
Summary: Python and Django Project Utils Package
Home-page: https://github.com/Ayobami6/sparky_utils
Author: Ayobami Alaran
Author-email: ayobamidele006@gmail.com
Classifier: Programming Language :: Python :: 3
Classifier: License :: OSI Approved :: MIT License
Classifier: Operating System :: OS Independent
Requires-Python: >=3.6
License-File: LICENSE
Dynamic: author
Dynamic: author-email
Dynamic: classifier
Dynamic: description
Dynamic: description-content-type
Dynamic: home-page
Dynamic: requires-python
Dynamic: summary
